hundred/__init__.py
hundred/application/__init__.py
hundred/application/paginated_list.py
hundred/contrib/__init__.py
hundred/contrib/_pytest/__init__.py
hundred/contrib/_pytest/plugin.py
hundred/ctx/__init__.py
hundred/ctx/auth/__init__.py
hundred/ctx/auth/aliases.py
hundred/ctx/auth/commands/__init__.py
hundred/ctx/auth/commands/change_password.py
hundred/ctx/auth/commands/forgot_password.py
hundred/ctx/auth/commands/login.py
hundred/ctx/auth/commands/logout.py
hundred/ctx/auth/commands/new_user.py
hundred/ctx/auth/commands/refresh.py
hundred/ctx/auth/commands/reset_password.py
hundred/ctx/auth/commands/send_check_code.py
hundred/ctx/auth/commands/verify_check_code.py
hundred/ctx/auth/domain/__init__.py
hundred/ctx/auth/domain/check_code.py
hundred/ctx/auth/domain/session.py
hundred/ctx/auth/domain/session_status.py
hundred/ctx/auth/domain/user.py
hundred/ctx/auth/domain/user_status.py
hundred/ctx/auth/dto/__init__.py
hundred/ctx/auth/dto/authenticated.py
hundred/ctx/auth/factories/__init__.py
hundred/ctx/auth/factories/check_code_factory.py
hundred/ctx/auth/factories/session_factory.py
hundred/ctx/auth/factories/user_factory.py
hundred/ctx/auth/ports/__init__.py
hundred/ctx/auth/ports/generate_pin.py
hundred/ctx/auth/ports/session_repository.py
hundred/ctx/auth/ports/two_factor_authenticator.py
hundred/ctx/auth/ports/user_repository.py
hundred/ctx/auth/services/__init__.py
hundred/ctx/auth/services/session_service.py
hundred/domain/__init__.py
hundred/domain/entity.py
hundred/domain/vo.py
hundred/exceptions.py
hundred/gettext.py
hundred/lang/en/LC_MESSAGES/messages.mo
hundred/lang/fr/LC_MESSAGES/messages.mo
hundred/py.typed
hundred/services/__init__.py
hundred/services/authenticator.py
hundred/services/datetime.py
hundred/services/hasher.py
hundred/services/i18n.py
hundred/services/token.py
hundred/services/uuid.py
hundred/testing/__init__.py
hundred/testing/adapter/__init__.py
hundred/testing/adapter/repository.py
hundred/testing/adapters/__init__.py
hundred-0.5.3.dist-info/METADATA
hundred-0.5.3.dist-info/WHEEL
hundred-0.5.3.dist-info/entry_points.txt
hundred-0.5.3.dist-info/RECORD
