Metadata-Version: 2.1
Name: Hundred
Version: 0.5.3
Summary: 
Home-page: https://github.com/100nm/hundred
Author: remimd
Requires-Python: >=3.12,<4
Classifier: Programming Language :: Python :: 3
Classifier: Programming Language :: Python :: 3.12
Classifier: Programming Language :: Python :: 3.13
Provides-Extra: testing
Requires-Dist: argon2-cffi
Requires-Dist: babel
Requires-Dist: faker ; extra == "testing"
Requires-Dist: orjson ; extra == "testing"
Requires-Dist: pydantic (>=2,<3)
Requires-Dist: pyjwt
Requires-Dist: python-cq
Requires-Dist: python-injection
Requires-Dist: python-ulid
Project-URL: Repository, https://github.com/100nm/hundred
